{
  "version": 1,
  "generatedAt": "2026-04-25T20:30:00.000Z",
  "intent": "Manual verification registry for all internet research sources used by the app for ingestion and theory validation.",
  "sources": [
    {
      "sourceId": "szaza-c-major",
      "provider": "szaza/guitar-chords-db-json",
      "datasetUrl": "https://raw.githubusercontent.com/szaza/guitar-chords-db-json/master/C/major.json",
      "license": "MIT",
      "licenseUrl": "https://github.com/szaza/guitar-chords-db-json/blob/master/LICENSE",
      "sourceType": "dataset_ingest",
      "usage": "Primary chord voicing ingestion for C major.",
      "format": "szaza_chord_positions",
      "tuningId": "standard",
      "validatesWith": ["tombatossals-c-major"],
      "fallbackSources": ["tombatossals-c-major"],
      "manualCheck": "Open datasetUrl and confirm key='C', suffix='major', and positions[] exists."
    },
    {
      "sourceId": "szaza-g-major",
      "provider": "szaza/guitar-chords-db-json",
      "datasetUrl": "https://raw.githubusercontent.com/szaza/guitar-chords-db-json/master/G/major.json",
      "license": "MIT",
      "licenseUrl": "https://github.com/szaza/guitar-chords-db-json/blob/master/LICENSE",
      "sourceType": "dataset_ingest",
      "usage": "Primary chord voicing ingestion for G major.",
      "format": "szaza_chord_positions",
      "tuningId": "standard",
      "validatesWith": ["tombatossals-g-major"],
      "fallbackSources": ["tombatossals-g-major"],
      "manualCheck": "Open datasetUrl and confirm key='G', suffix='major', and positions[] exists."
    },
    {
      "sourceId": "szaza-d-major",
      "provider": "szaza/guitar-chords-db-json",
      "datasetUrl": "https://raw.githubusercontent.com/szaza/guitar-chords-db-json/master/D/major.json",
      "license": "MIT",
      "licenseUrl": "https://github.com/szaza/guitar-chords-db-json/blob/master/LICENSE",
      "sourceType": "dataset_ingest",
      "usage": "Primary chord voicing ingestion for D major.",
      "format": "szaza_chord_positions",
      "tuningId": "standard",
      "validatesWith": ["tombatossals-d-major"],
      "fallbackSources": ["tombatossals-d-major"],
      "manualCheck": "Open datasetUrl and confirm key='D', suffix='major', and positions[] exists."
    },
    {
      "sourceId": "szaza-a-major",
      "provider": "szaza/guitar-chords-db-json",
      "datasetUrl": "https://raw.githubusercontent.com/szaza/guitar-chords-db-json/master/A/major.json",
      "license": "MIT",
      "licenseUrl": "https://github.com/szaza/guitar-chords-db-json/blob/master/LICENSE",
      "sourceType": "dataset_ingest",
      "usage": "Primary chord voicing ingestion for A major.",
      "format": "szaza_chord_positions",
      "tuningId": "standard",
      "validatesWith": ["tombatossals-a-major"],
      "fallbackSources": ["tombatossals-a-major"],
      "manualCheck": "Open datasetUrl and confirm key='A', suffix='major', and positions[] exists."
    },
    {
      "sourceId": "szaza-e-major",
      "provider": "szaza/guitar-chords-db-json",
      "datasetUrl": "https://raw.githubusercontent.com/szaza/guitar-chords-db-json/master/E/major.json",
      "license": "MIT",
      "licenseUrl": "https://github.com/szaza/guitar-chords-db-json/blob/master/LICENSE",
      "sourceType": "dataset_ingest",
      "usage": "Primary chord voicing ingestion for E major.",
      "format": "szaza_chord_positions",
      "tuningId": "standard",
      "validatesWith": ["tombatossals-e-major"],
      "fallbackSources": ["tombatossals-e-major"],
      "manualCheck": "Open datasetUrl and confirm key='E', suffix='major', and positions[] exists."
    },
    {
      "sourceId": "szaza-f-major",
      "provider": "szaza/guitar-chords-db-json",
      "datasetUrl": "https://raw.githubusercontent.com/szaza/guitar-chords-db-json/master/F/major.json",
      "license": "MIT",
      "licenseUrl": "https://github.com/szaza/guitar-chords-db-json/blob/master/LICENSE",
      "sourceType": "dataset_ingest",
      "usage": "Primary chord voicing ingestion for F major.",
      "format": "szaza_chord_positions",
      "tuningId": "standard",
      "validatesWith": ["tombatossals-f-major"],
      "fallbackSources": ["tombatossals-f-major"],
      "manualCheck": "Open datasetUrl and confirm key='F', suffix='major', and positions[] exists."
    },
    {
      "sourceId": "tombatossals-c-major",
      "provider": "tombatossals/chords-db",
      "datasetUrl": "https://raw.githubusercontent.com/tombatossals/chords-db/master/lib/guitar.json",
      "license": "MIT",
      "licenseUrl": "https://github.com/tombatossals/chords-db/blob/master/LICENSE",
      "sourceType": "dataset_validator",
      "usage": "Cross-source validation fallback for C major voicings sourced from szaza.",
      "format": "tombatossals_guitar_lib",
      "tuningId": "standard",
      "manualCheck": "Open datasetUrl and verify chords.C includes suffix='major' entries with positions[]."
    },
    {
      "sourceId": "tombatossals-g-major",
      "provider": "tombatossals/chords-db",
      "datasetUrl": "https://raw.githubusercontent.com/tombatossals/chords-db/master/lib/guitar.json",
      "license": "MIT",
      "licenseUrl": "https://github.com/tombatossals/chords-db/blob/master/LICENSE",
      "sourceType": "dataset_validator",
      "usage": "Cross-source validation fallback for G major voicings sourced from szaza.",
      "format": "tombatossals_guitar_lib",
      "tuningId": "standard",
      "manualCheck": "Open datasetUrl and verify chords.G includes suffix='major' entries with positions[]."
    },
    {
      "sourceId": "tombatossals-d-major",
      "provider": "tombatossals/chords-db",
      "datasetUrl": "https://raw.githubusercontent.com/tombatossals/chords-db/master/lib/guitar.json",
      "license": "MIT",
      "licenseUrl": "https://github.com/tombatossals/chords-db/blob/master/LICENSE",
      "sourceType": "dataset_validator",
      "usage": "Cross-source validation fallback for D major voicings sourced from szaza.",
      "format": "tombatossals_guitar_lib",
      "tuningId": "standard",
      "manualCheck": "Open datasetUrl and verify chords.D includes suffix='major' entries with positions[]."
    },
    {
      "sourceId": "tombatossals-a-major",
      "provider": "tombatossals/chords-db",
      "datasetUrl": "https://raw.githubusercontent.com/tombatossals/chords-db/master/lib/guitar.json",
      "license": "MIT",
      "licenseUrl": "https://github.com/tombatossals/chords-db/blob/master/LICENSE",
      "sourceType": "dataset_validator",
      "usage": "Cross-source validation fallback for A major voicings sourced from szaza.",
      "format": "tombatossals_guitar_lib",
      "tuningId": "standard",
      "manualCheck": "Open datasetUrl and verify chords.A includes suffix='major' entries with positions[]."
    },
    {
      "sourceId": "tombatossals-e-major",
      "provider": "tombatossals/chords-db",
      "datasetUrl": "https://raw.githubusercontent.com/tombatossals/chords-db/master/lib/guitar.json",
      "license": "MIT",
      "licenseUrl": "https://github.com/tombatossals/chords-db/blob/master/LICENSE",
      "sourceType": "dataset_validator",
      "usage": "Cross-source validation fallback for E major voicings sourced from szaza.",
      "format": "tombatossals_guitar_lib",
      "tuningId": "standard",
      "manualCheck": "Open datasetUrl and verify chords.E includes suffix='major' entries with positions[]."
    },
    {
      "sourceId": "tombatossals-f-major",
      "provider": "tombatossals/chords-db",
      "datasetUrl": "https://raw.githubusercontent.com/tombatossals/chords-db/master/lib/guitar.json",
      "license": "MIT",
      "licenseUrl": "https://github.com/tombatossals/chords-db/blob/master/LICENSE",
      "sourceType": "dataset_validator",
      "usage": "Cross-source validation fallback for F major voicings sourced from szaza.",
      "format": "tombatossals_guitar_lib",
      "tuningId": "standard",
      "manualCheck": "Open datasetUrl and verify chords.F includes suffix='major' entries with positions[]."
    },
    {
      "sourceId": "open-music-theory",
      "provider": "Open Music Theory",
      "datasetUrl": "https://openmusictheory.github.io/",
      "license": "CC BY-SA 4.0",
      "licenseUrl": "https://creativecommons.org/licenses/by-sa/4.0/",
      "sourceType": "theory_reference",
      "usage": "Theory definitions and conceptual validation for scales, harmony, and notation behavior.",
      "format": "reference_site",
      "manualCheck": "Open site and verify footer indicates CC BY-SA 4.0 and content relevance to implemented theory."
    },
    {
      "sourceId": "teoria-reference",
      "provider": "teoria.com",
      "datasetUrl": "https://www.teoria.com/",
      "license": "CC BY-NC-ND 4.0",
      "licenseUrl": "https://creativecommons.org/licenses/by-nc-nd/4.0/",
      "sourceType": "theory_reference",
      "usage": "Cross-check reference for chord names, intervals, and harmony terminology in UI explanations.",
      "format": "reference_site",
      "manualCheck": "Open site and verify Creative Commons BY-NC-ND notice in footer."
    },
    {
      "sourceId": "musictheory-net",
      "provider": "musictheory.net",
      "datasetUrl": "https://www.musictheory.net/",
      "license": "Proprietary",
      "licenseUrl": "https://www.musictheory.net/legal",
      "sourceType": "theory_reference",
      "usage": "Pedagogical cross-check for lesson sequencing and beginner-facing explanation quality.",
      "format": "reference_site",
      "manualCheck": "Open site and legal page; confirm this source is used for conceptual reference only and not ingested."
    },
    {
      "sourceId": "wikipedia-nashville-number-system",
      "provider": "Wikipedia",
      "datasetUrl": "https://en.wikipedia.org/wiki/Nashville_Number_System",
      "license": "CC BY-SA 4.0",
      "licenseUrl": "https://creativecommons.org/licenses/by-sa/4.0/",
      "sourceType": "theory_reference",
      "usage": "Historical and notation reference for Nashville Number System features in translator and table UI.",
      "format": "reference_site",
      "manualCheck": "Open article and validate that implemented NNS notation behavior aligns with documented usage."
    },
    {
      "sourceId": "wikipedia-circle-of-fifths",
      "provider": "Wikipedia",
      "datasetUrl": "https://en.wikipedia.org/wiki/Circle_of_fifths",
      "license": "CC BY-SA 4.0",
      "licenseUrl": "https://creativecommons.org/licenses/by-sa/4.0/",
      "sourceType": "theory_reference",
      "usage": "Reference for circle-of-fifths relationships used in key navigation visuals.",
      "format": "reference_site",
      "manualCheck": "Open article and validate clockwise/counterclockwise key relations used in the app."
    },
    {
      "sourceId": "music-theory-21st-century-classroom",
      "provider": "University of Puget Sound",
      "datasetUrl": "https://musictheory.pugetsound.edu/",
      "license": "GNU Free Documentation License",
      "licenseUrl": "https://www.gnu.org/licenses/fdl-1.3.en.html",
      "sourceType": "theory_reference",
      "usage": "Modern theory pedagogy reference for fine-tuning explanatory content and educational flow.",
      "format": "reference_site",
      "manualCheck": "Open site and verify license attribution in publication notes before using derived textual explanations."
    }
  ]
}
